changeos/__init__.py
changeos-0.2.dist-info/METADATA
changeos-0.2.dist-info/WHEEL
changeos-0.2.dist-info/top_level.txt
changeos-0.2.dist-info/RECORD
